harmonize_ds/__init__.py
harmonize_ds/cli.py
harmonize_ds/harmonize.py
harmonize_ds/utils.py
harmonize_ds/version.py
harmonize_ds/config/config.yaml
harmonize_ds/manager/__init__.py
harmonize_ds/manager/datasource_factory.py
harmonize_ds/manager/datasource_manager.py
harmonize_ds/sources/__init__.py
harmonize_ds/sources/base.py
harmonize_ds/sources/wcs.py
harmonize_ds/sources/wfs.py
harmonize_ds/templates/harmonize_ds.html
harmonize_ds/templates/metadata.html
harmonize_ds-0.4.0.dist-info/licenses/LICENSE
harmonize_ds-0.4.0.dist-info/METADATA
harmonize_ds-0.4.0.dist-info/WHEEL
harmonize_ds-0.4.0.dist-info/entry_points.txt
harmonize_ds-0.4.0.dist-info/top_level.txt
harmonize_ds-0.4.0.dist-info/RECORD
