Metadata-Version: 2.4
Name: harmonize-ds
Version: 0.4.0
Summary: .
Author-email: Harmonize Brazil Team <bdc.team@inpe.br>
License: GNU GENERAL PUBLIC LICENSE
Keywords: lulc
Classifier: Intended Audience :: Information Technology
Classifier: Intended Audience :: Science/Research
Classifier: License :: OSI Approved :: GNU General Public License v3 (GPLv3)
Classifier: Programming Language :: Python :: 3.8
Classifier: Programming Language :: Python :: 3.9
Classifier: Programming Language :: Python :: 3.10
Classifier: Programming Language :: Python :: 3.11
Classifier: Programming Language :: Python :: 3.12
Classifier: Topic :: Software Development :: Libraries :: Python Modules
Requires-Python: >=3.10
License-File: LICENSE
Requires-Dist: jinja2<4.0.0,>=3.1.5
Requires-Dist: click<9.0.0,>=8.1.8
Requires-Dist: geopandas<2.0.0,>=1.0.1
Requires-Dist: pandas<3.0.0,>=2.2.3
Requires-Dist: httpx<0.29.0,>=0.28.1
Requires-Dist: pystac-client<0.9.0,>=0.8.5
Requires-Dist: PyYAML==6.0.2
Requires-Dist: owslib<0.33.0,>=0.32.1
Requires-Dist: rich<14.0.0,>=13.9.4
Requires-Dist: wlts.py>=1.0
Requires-Dist: matplotlib>=3.10.6
Provides-Extra: dev
Requires-Dist: pre-commit; extra == "dev"
Provides-Extra: docs
Requires-Dist: Sphinx>=7.0; extra == "docs"
Requires-Dist: sphinx_rtd_theme; extra == "docs"
Requires-Dist: sphinx-copybutton; extra == "docs"
Requires-Dist: sphinx-tabs; extra == "docs"
Provides-Extra: tests
Requires-Dist: coverage>=6.4; extra == "tests"
Requires-Dist: coveralls>=3.3; extra == "tests"
Requires-Dist: pytest>=7.4; extra == "tests"
Requires-Dist: pytest-cov>=4.1; extra == "tests"
Requires-Dist: pytest-pep8>=1.0; extra == "tests"
Requires-Dist: pydocstyle>=4.0; extra == "tests"
Requires-Dist: isort>4.3; extra == "tests"
Requires-Dist: check-manifest>=0.40; extra == "tests"
Provides-Extra: all
Requires-Dist: harmonize_ds[docs,tests]; extra == "all"
Dynamic: license-file
